[
    {
        "InstitutionId": 624,
        "InstitutionName": "Akwa Ibom State College Of Arts And Science Nung"
    },
    {
        "InstitutionId": 1103,
        "InstitutionName": "Akwa Ibom State University"
    },
    {
        "InstitutionId": 623,
        "InstitutionName": "Akwa-Ibom State College Of Agriculture Obio-Akpa"
    },
    {
        "InstitutionId": 825,
        "InstitutionName": "Akwa-Ibom State College Of Education"
    },
    {
        "InstitutionId": 625,
        "InstitutionName": "Akwa-Ibom State Polytechnic"
    },
    {
        "InstitutionId": 1258,
        "InstitutionName": "FEDERAL UNIVERSITY OF TECHNOLOGY IKOTABASI - FUTIA"
    },
    {
        "InstitutionId": 707,
        "InstitutionName": "Heritage Polytechnic"
    },
    {
        "InstitutionId": 712,
        "InstitutionName": "Imfi, Ict Academy"
    },
    {
        "InstitutionId": 1131,
        "InstitutionName": "Maritime Academy of Nigeria, Oron"
    },
    {
        "InstitutionId": 574,
        "InstitutionName": "Obong University, Obong, Ntak"
    },
    {
        "InstitutionId": 1178,
        "InstitutionName": "Ritman University"
    },
    {
        "InstitutionId": 958,
        "InstitutionName": "School of Midwifery, Anua-Uyo"
    },
    {
        "InstitutionId": 972,
        "InstitutionName": "School of Midwifery, Iquita-Onon"
    },
    {
        "InstitutionId": 973,
        "InstitutionName": "School of Midwifery, Ituk-Mbang"
    },
    {
        "InstitutionId": 1003,
        "InstitutionName": "School of Midwifery, Urua-Akpan"
    },
    {
        "InstitutionId": 1029,
        "InstitutionName": "School of Nursing, General Hospital, Ikot-Ekpene"
    },
    {
        "InstitutionId": 1040,
        "InstitutionName": "School of Nursing,Immanuel Hospital, Eket"
    },
    {
        "InstitutionId": 1041,
        "InstitutionName": "School of Nursing,Ituk-Mbang,"
    },
    {
        "InstitutionId": 1061,
        "InstitutionName": "School of Nursing,St.  Luke\u0027s Hospital, Anua Uyo"
    },
    {
        "InstitutionId": 1076,
        "InstitutionName": "School of Psychiatric Nursing, Eket"
    },
    {
        "InstitutionId": 937,
        "InstitutionName": "St-Joseph Major Seminary"
    },
    {
        "InstitutionId": 1237,
        "InstitutionName": "Topfaith University"
    },
    {
        "InstitutionId": 605,
        "InstitutionName": "University Of Uyo"
    }
]